keycloak/__init__.py
keycloak/connection.py
keycloak/exceptions.py
keycloak/keycloak_admin.py
keycloak/keycloak_openid.py
keycloak/urls_patterns.py
keycloak/authorization/__init__.py
keycloak/authorization/permission.py
keycloak/authorization/policy.py
keycloak/authorization/role.py
keycloak/tests/__init__.py
keycloak/tests/test_connection.py
async_keycloak-0.28.4.dist-info/LICENSE
async_keycloak-0.28.4.dist-info/METADATA
async_keycloak-0.28.4.dist-info/WHEEL
async_keycloak-0.28.4.dist-info/top_level.txt
async_keycloak-0.28.4.dist-info/RECORD
