Metadata-Version: 2.1
Name: async-keycloak
Version: 0.28.4
Summary: async-keycloak is a fork of python-keycloak with asyncio support using httpx
Home-page: https://github.com/jegork/python-keycloak
Author: Jegor Kitskerkin
Author-email: jegor.kitskerkin@gmail.com
License: The MIT License
Keywords: keycloak openid async httpx
Platform: UNKNOWN
Classifier: Programming Language :: Python :: 3
Classifier: License :: OSI Approved :: MIT License
Classifier: Development Status :: 3 - Alpha
Classifier: Operating System :: MacOS
Classifier: Operating System :: Unix
Classifier: Operating System :: Microsoft :: Windows
Classifier: Topic :: Utilities
License-File: LICENSE
Requires-Dist: httpx (>=0.22.0)
Requires-Dist: python-jose (>=1.4.0)
